comb_spec_searcher/__init__.py
comb_spec_searcher/bijection.py
comb_spec_searcher/class_db.py
comb_spec_searcher/class_queue.py
comb_spec_searcher/comb_spec_searcher.py
comb_spec_searcher/combinatorial_class.py
comb_spec_searcher/equiv_db.py
comb_spec_searcher/exception.py
comb_spec_searcher/isomorphism.py
comb_spec_searcher/proof_tree.py
comb_spec_searcher/py.typed
comb_spec_searcher/specification.py
comb_spec_searcher/specification_drawer.py
comb_spec_searcher/specification_extrator.py
comb_spec_searcher/tree_searcher.py
comb_spec_searcher/typing.py
comb_spec_searcher/utils.py
comb_spec_searcher/resources/static/css/bootstrap.css
comb_spec_searcher/resources/static/css/specification.css
comb_spec_searcher/resources/static/css/treant.css
comb_spec_searcher/resources/static/js/Treant.js
comb_spec_searcher/resources/static/js/bootstrap.bundle.min.js
comb_spec_searcher/resources/static/js/jquery.min.js
comb_spec_searcher/resources/static/js/raphael.js
comb_spec_searcher/rule_db/__init__.py
comb_spec_searcher/rule_db/abstract.py
comb_spec_searcher/rule_db/base.py
comb_spec_searcher/rule_db/forest.py
comb_spec_searcher/rule_db/forget.py
comb_spec_searcher/strategies/__init__.py
comb_spec_searcher/strategies/rule.py
comb_spec_searcher/strategies/strategy.py
comb_spec_searcher/strategies/strategy_pack.py
comb_spec_searcher/strategies/constructor/__init__.py
comb_spec_searcher/strategies/constructor/base.py
comb_spec_searcher/strategies/constructor/cartesian.py
comb_spec_searcher/strategies/constructor/disjoint.py
comb_spec_searcher-4.3.0.dist-info/METADATA
comb_spec_searcher-4.3.0.dist-info/WHEEL
comb_spec_searcher-4.3.0.dist-info/licenses/LICENSE.txt
comb_spec_searcher-4.3.0.dist-info/RECORD
