Metadata-Version: 2.4
Name: comb_spec_searcher
Version: 4.3.0
Summary: A library for performing combinatorial exploration.
Project-URL: Source, https://github.com/PermutaTriangle/comb_spec_searcher
Project-URL: Tracker, https://github.com/PermutaTriangle/comb_spec_searcher/issues
Author-email: Permuta Triangle <permutatriangle@gmail.com>
License: BSD-3-Clause
License-File: LICENSE.txt
Keywords: combinatorial,combinatorics,counting,enumerative,specification
Classifier: Development Status :: 5 - Production/Stable
Classifier: Intended Audience :: Education
Classifier: Intended Audience :: Science/Research
Classifier: License :: OSI Approved :: BSD License
Classifier: Programming Language :: Python :: 3
Classifier: Programming Language :: Python :: 3.10
Classifier: Programming Language :: Python :: 3.11
Classifier: Programming Language :: Python :: 3.12
Classifier: Programming Language :: Python :: 3.13
Classifier: Programming Language :: Python :: Implementation :: CPython
Classifier: Programming Language :: Python :: Implementation :: PyPy
Classifier: Topic :: Education
Classifier: Topic :: Scientific/Engineering :: Mathematics
Requires-Python: >=3.10
Requires-Dist: logzero==1.7.0
Requires-Dist: psutil==7.0.0
Requires-Dist: pympler==1.1
Requires-Dist: requests==2.32.4
Requires-Dist: sympy==1.14.0
Requires-Dist: tabulate==0.9.0
Requires-Dist: typing-extensions==4.14.0
